src/mouse.v
`timescale 1ns / 1ps
//////////////////////////////////////////////////////////////////////////////////
// Company: 
// Engineer: 
// 
// Create Date: 09.03.2026 11:33:11
// Design Name: 
// Module Name: mouse
// Project Name: 
// Target Devices: 
// Tool Versions: 
// Description: 
// 
// Dependencies: 
// 
// Revision:
// Revision 0.01 - File Created
// Additional Comments:
// 
//////////////////////////////////////////////////////////////////////////////////


module mouse(
    input        clk,              // System Clock (100 MHz)
    input        rst,              // Active-high reset
    input        mouse_data,       // PS/2 Data from mouse
    input        mouse_clk,        // PS/2 Clk from mouse
    
    output [7:0] x_pos,            // X pos [0, +255] 
    output [7:0] y_pos,            // Y pos [0, +255]
    output x_sign, y_sign,         // Sign of the X & Y Position
    output       left_btn,         // Left button state
    output       right_btn,        // Right button state
    output       middle_btn        // Middle button state
    );
    
    // --- Internal registers --------------------------------------
    wire [10:0]  word1, word2, word3, word4;
    wire [7:0]   signal1, signal2, signal3, signal4;
    wire         val;
    
    assign ready = val && ack;
    
    
    // --- Map Signals ---------------------------------------------
    // Note: PS/2 sends LSB first, so we reverse the bits when extracting
    assign x_pos = {signal2[0], signal2[1], signal2[2], signal2[3], signal2[4], signal2[5], signal2[6], signal2[7]};
    assign y_pos = {signal3[0], signal3[1], signal3[2], signal3[3], signal3[4], signal3[5], signal3[6], signal3[7]};
    assign x_sign = signal1[3];  // Bit 4 of status byte
    assign y_sign = signal1[2];  // Bit 5 of status byte
    assign left_btn = signal1[7]; // Bit 0 of status byte
    assign right_btn = signal1[6]; // Bit 1 of status byte
    assign middle_btn = signal1[5]; // Bit 2 of status byte 
    
    
    // --- Signal Processing ---------------------------------------
    reg [43:0]  fifo;
    reg [43:0]  buffer;
    reg [5:0]   counter;
    reg [1:0]   PS2Clk_sync;
    reg         PS2Data;
    reg         ack;
    wire        PS2Clk_negedge;
    
    assign word1 = fifo[33 +: 11];
    assign word2 = fifo[22 +: 11];
    assign word3 = fifo[11 +: 11];
    assign word4 = fifo[0 +: 11];
    
    assign PS2Clk_negedge = (PS2Clk_sync == 2'b10);
    
    initial begin
        fifo <= 44'b0;
        buffer <= 44'b0;
        counter <= 6'b0;
        PS2Clk_sync <= 2'b1;
        ack <= 1'b0;
        PS2Data <= 1'b0;
    end
    
    always @(posedge clk) begin 
        if (rst) begin
            fifo <= 44'b0;
            buffer <= 44'b0;
            counter <= 6'b0;
            ack <= 1'b0;
            PS2Clk_sync <= 2'b11;
            PS2Data <= 1'b0;
        end else begin
            // Synchronize PS/2 clock
            PS2Clk_sync <= {PS2Clk_sync[0], mouse_clk};
            PS2Data <= mouse_data;
            
            if (PS2Clk_negedge) begin
                buffer <= {buffer[42:0], PS2Data};
                counter <= counter + 6'b1;
            end
            
            if (counter == 6'd44) begin
                // Counter == 44 --> Buffer is FULL
                fifo <= buffer;
                buffer <= 44'b0;
                counter <= 6'b0;
                ack <= 1'b1;
            end else begin
                // Counter != 44 --> clear ack flag
                ack <= 1'b0;
            end
        end
    end


    // --- Signal Validation ---------------------------------------
    wire parity1, parity2, parity3, parity4, parity;
    wire start1, start2, start3, start4, start;
    wire stop1, stop2, stop3, stop4, stop;
    wire valid1, valid2, valid3, valid4;

    // Separate packets into segments
    assign {start1, signal1, parity1, stop1} = word1;
    assign {start2, signal2, parity2, stop2} = word2;
    assign {start3, signal3, parity3, stop3} = word3;
    assign {start4, signal4, parity4, stop4} = word4;
    
    // XNOR words together and compare to parity bit
    assign valid1 = ~^signal1 == parity1;
    assign valid2 = ~^signal2 == parity2;
    assign valid3 = ~^signal3 == parity3;
    assign valid4 = ~^signal4 == parity4;
    
    assign parity = valid1 && valid2 && valid3 && valid4;
    assign start = (!start1 && !start2 && !start3 && !start4);
    assign stop = (stop1 && stop2 && stop3 && stop4);
    assign o_valid = (start && stop && parity);

endmodule

tb/mouse_tb.v
`timescale 1ns / 1ps
//////////////////////////////////////////////////////////////////////////////////
// Testbench: mouse_tb
// Description: Self-checking testbench for PS/2 mouse interface
// Tests:
//   - PS/2 packet transmission (44-bit frame)
//   - Parity bit validation
//   - X/Y position extraction
//   - X/Y sign bit handling
//   - Button state detection (left, right, middle)
//   - Multiple packet sequences
//////////////////////////////////////////////////////////////////////////////////

module mouse_tb;

    // Testbench signals
    reg         clk;
    reg         rst;
    reg         mouse_data;
    reg         mouse_clk;
    
    wire [7:0]  x_pos;
    wire [7:0]  y_pos;
    wire        x_sign;
    wire        y_sign;
    wire        left_btn;
    wire        right_btn;
    wire        middle_btn;
    
    // Test control
    integer     test_count;
    integer     pass_count;
    integer     fail_count;
    
    // Instantiate the Unit Under Test
    mouse uut (
        .clk(clk),
        .rst(rst),
        .mouse_data(mouse_data),
        .mouse_clk(mouse_clk),
        .x_pos(x_pos),
        .y_pos(y_pos),
        .x_sign(x_sign),
        .y_sign(y_sign),
        .left_btn(left_btn),
        .right_btn(right_btn),
        .middle_btn(middle_btn)
    );
    
    // Clock generation (100 MHz system clock)
    initial begin
        clk = 0;
        forever #5 clk = ~clk;  // 10ns period = 100MHz
    end
    
    // PS/2 Clock generation (separate from system clock)
    initial begin
        mouse_clk = 1;
    end
    
    // Task: Generate PS/2 clock pulse
    task ps2_clock_pulse;
        begin
            #100 mouse_clk = 0;  // PS/2 clock typically 10-16.7 kHz
            #100 mouse_clk = 1;
        end
    endtask
    
    // Task: Send a single 11-bit PS/2 packet (start + 8 data + parity + stop)
    task send_ps2_packet;
        input [7:0] data;
        reg parity_bit;
        integer i;
        begin
            // Calculate odd parity
            parity_bit = ~^data;
            
            // Start bit (0)
            mouse_data = 0;
            ps2_clock_pulse();
            
            // Data bits (LSB first)
            for (i = 0; i < 8; i = i + 1) begin
                mouse_data = data[i];
                ps2_clock_pulse();
            end
            
            // Parity bit
            mouse_data = parity_bit;
            ps2_clock_pulse();
            
            // Stop bit (1)
            mouse_data = 1;
            ps2_clock_pulse();
        end
    endtask
    
    // Task: Send complete mouse movement packet (4 packets of 11 bits = 44 bits)
    // Packet format:
    //   Byte 1: [Y_overflow, X_overflow, Y_sign, X_sign, 1, Middle_btn, Right_btn, Left_btn]
    //   Byte 2: X movement (0-255)
    //   Byte 3: Y movement (0-255)
    //   Byte 4: Z movement (scroll wheel) - usually 0x00
    task send_mouse_packet;
        input        l_btn, r_btn, m_btn;
        input        x_sgn, y_sgn;
        input [7:0]  x_mov, y_mov;
        reg [7:0]    byte1;
        begin
            // Construct status byte (Byte 1)
            byte1 = {2'b00, y_sgn, x_sgn, 1'b1, m_btn, r_btn, l_btn};
            
            $display("[TIME=%0t] Sending packet: L=%b R=%b M=%b X_sign=%b Y_sign=%b X=%d Y=%d", 
                     $time, l_btn, r_btn, m_btn, x_sgn, y_sgn, x_mov, y_mov);
            
            // Send 4 packets
            send_ps2_packet(byte1);      // Status byte
            send_ps2_packet(x_mov);      // X movement
            send_ps2_packet(y_mov);      // Y movement
            send_ps2_packet(8'h00);      // Z movement (wheel)
            
            // Wait for processing
            #2000;
        end
    endtask
    
    // Task: Check output values
    task check_output;
        input [7:0]  exp_x, exp_y;
        input        exp_x_sign, exp_y_sign;
        input        exp_left, exp_right, exp_middle;
        input [200*8:1] test_name;
        begin
            test_count = test_count + 1;
            
            if (x_pos === exp_x && y_pos === exp_y && 
                x_sign === exp_x_sign && y_sign === exp_y_sign &&
                left_btn === exp_left && right_btn === exp_right && 
                middle_btn === exp_middle) begin
                $display("[PASS] Test %0d: %0s", test_count, test_name);
                $display("       Expected: X=%d Y=%d X_sign=%b Y_sign=%b L=%b R=%b M=%b",
                         exp_x, exp_y, exp_x_sign, exp_y_sign, exp_left, exp_right, exp_middle);
                $display("       Got:      X=%d Y=%d X_sign=%b Y_sign=%b L=%b R=%b M=%b",
                         x_pos, y_pos, x_sign, y_sign, left_btn, right_btn, middle_btn);
                pass_count = pass_count + 1;
            end else begin
                $display("[FAIL] Test %0d: %0s", test_count, test_name);
                $display("       Expected: X=%d Y=%d X_sign=%b Y_sign=%b L=%b R=%b M=%b",
                         exp_x, exp_y, exp_x_sign, exp_y_sign, exp_left, exp_right, exp_middle);
                $display("       Got:      X=%d Y=%d X_sign=%b Y_sign=%b L=%b R=%b M=%b",
                         x_pos, y_pos, x_sign, y_sign, left_btn, right_btn, middle_btn);
                fail_count = fail_count + 1;
            end
            $display("");
        end
    endtask
    
    // Main test sequence
    initial begin
        // Initialize signals
        rst = 1;
        mouse_data = 1;
        test_count = 0;
        pass_count = 0;
        fail_count = 0;
        
        $display("========================================");
        $display("  PS/2 Mouse Interface Testbench");
        $display("========================================");
        $display("");
        
        // Hold reset
        #200;
        rst = 0;
        #100;
        
        // Test 1: Basic movement - positive X, positive Y, no buttons
        $display("--- Test 1: Positive X/Y movement, no buttons ---");
        send_mouse_packet(0, 0, 0, 0, 0, 8'd10, 8'd20);
        check_output(8'd10, 8'd20, 1'b0, 1'b0, 1'b0, 1'b0, 1'b0, 
                     "Positive X/Y movement");
        
        // Test 2: Negative X movement (sign bit set)
        $display("--- Test 2: Negative X movement ---");
        send_mouse_packet(0, 0, 0, 1, 0, 8'd5, 8'd15);
        check_output(8'd5, 8'd15, 1'b1, 1'b0, 1'b0, 1'b0, 1'b0,
                     "Negative X movement");
        
        // Test 3: Negative Y movement (sign bit set)
        $display("--- Test 3: Negative Y movement ---");
        send_mouse_packet(0, 0, 0, 0, 1, 8'd25, 8'd30);
        check_output(8'd25, 8'd30, 1'b0, 1'b1, 1'b0, 1'b0, 1'b0,
                     "Negative Y movement");
        
        // Test 4: Left button click
        $display("--- Test 4: Left button click ---");
        send_mouse_packet(1, 0, 0, 0, 0, 8'd0, 8'd0);
        check_output(8'd0, 8'd0, 1'b0, 1'b0, 1'b1, 1'b0, 1'b0,
                     "Left button click");
        
        // Test 5: Right button click
        $display("--- Test 5: Right button click ---");
        send_mouse_packet(0, 1, 0, 0, 0, 8'd0, 8'd0);
        check_output(8'd0, 8'd0, 1'b0, 1'b0, 1'b0, 1'b1, 1'b0,
                     "Right button click");
        
        // Test 6: Middle button click
        $display("--- Test 6: Middle button click ---");
        send_mouse_packet(0, 0, 1, 0, 0, 8'd0, 8'd0);
        check_output(8'd0, 8'd0, 1'b0, 1'b0, 1'b0, 1'b0, 1'b1,
                     "Middle button click");
        
        // Test 7: Multiple buttons + movement
        $display("--- Test 7: Multiple buttons with movement ---");
        send_mouse_packet(1, 1, 0, 1, 1, 8'd50, 8'd100);
        check_output(8'd50, 8'd100, 1'b1, 1'b1, 1'b1, 1'b1, 1'b0,
                     "Dual button + negative movement");
        
        // Test 8: Maximum values
        $display("--- Test 8: Maximum X/Y values ---");
        send_mouse_packet(0, 0, 0, 0, 0, 8'd255, 8'd255);
        check_output(8'd255, 8'd255, 1'b0, 1'b0, 1'b0, 1'b0, 1'b0,
                     "Maximum X/Y values");
        
        // Test 9: Sequential packets (simulate continuous mouse movement)
        $display("--- Test 9: Sequential packet transmission ---");
        send_mouse_packet(0, 0, 0, 0, 0, 8'd1, 8'd1);
        check_output(8'd1, 8'd1, 1'b0, 1'b0, 1'b0, 1'b0, 1'b0,
                     "Sequential packet 1");
        
        send_mouse_packet(0, 0, 0, 0, 0, 8'd2, 8'd2);
        check_output(8'd2, 8'd2, 1'b0, 1'b0, 1'b0, 1'b0, 1'b0,
                     "Sequential packet 2");
        
        // Final summary
        $display("========================================");
        $display("  Test Summary");
        $display("========================================");
        $display("Total Tests: %0d", test_count);
        $display("Passed:      %0d", pass_count);
        $display("Failed:      %0d", fail_count);
        $display("========================================");
        
        if (fail_count == 0) begin
            $display("[SUCCESS] All tests passed!");
        end else begin
            $display("[FAILURE] Some tests failed. Review output above.");
        end
        
        $display("");
        $finish;
    end
    
    // Timeout watchdog
    initial begin
        #120000000;  // Increased timeout for sequential tests
        $display("[ERROR] Testbench timeout!");
        $finish;
    end
    
    // Waveform dump for GTKWave
    initial begin
        $dumpfile("waves.vcd");
        $dumpvars(0, mouse_tb);
    end

endmodule

waves.vcd
$date
	Tue Mar 24 12:04:11 2026
$end
$version
	Icarus Verilog
$end
$timescale
	1ps
$end
$scope module mouse_tb $end
$var wire 1 ! y_sign $end
$var wire 8 " y_pos [7:0] $end
$var wire 1 # x_sign $end
$var wire 8 $ x_pos [7:0] $end
$var wire 1 % right_btn $end
$var wire 1 & middle_btn $end
$var wire 1 ' left_btn $end
$var reg 1 ( clk $end
$var reg 1 ) mouse_clk $end
$var reg 1 * mouse_data $end
$var reg 1 + rst $end
$var integer 32 , fail_count [31:0] $end
$var integer 32 - pass_count [31:0] $end
$var integer 32 . test_count [31:0] $end
$scope module uut $end
$var wire 1 ( clk $end
$var wire 1 ) mouse_clk $end
$var wire 1 * mouse_data $end
$var wire 1 / o_valid $end
$var wire 1 0 parity $end
$var wire 1 1 ready $end
$var wire 1 + rst $end
$var wire 1 2 start $end
$var wire 1 3 stop $end
$var wire 1 4 val $end
$var wire 1 5 valid1 $end
$var wire 1 6 valid2 $end
$var wire 1 7 valid3 $end
$var wire 1 8 valid4 $end
$var wire 1 ! y_sign $end
$var wire 8 9 y_pos [7:0] $end
$var wire 1 # x_sign $end
$var wire 8 : x_pos [7:0] $end
$var wire 11 ; word4 [10:0] $end
$var wire 11 < word3 [10:0] $end
$var wire 11 = word2 [10:0] $end
$var wire 11 > word1 [10:0] $end
$var wire 1 ? stop4 $end
$var wire 1 @ stop3 $end
$var wire 1 A stop2 $end
$var wire 1 B stop1 $end
$var wire 1 C start4 $end
$var wire 1 D start3 $end
$var wire 1 E start2 $end
$var wire 1 F start1 $end
$var wire 8 G signal4 [7:0] $end
$var wire 8 H signal3 [7:0] $end
$var wire 8 I signal2 [7:0] $end
$var wire 8 J signal1 [7:0] $end
$var wire 1 % right_btn $end
$var wire 1 K parity4 $end
$var wire 1 L parity3 $end
$var wire 1 M parity2 $end
$var wire 1 N parity1 $end
$var wire 1 & middle_btn $end
$var wire 1 ' left_btn $end
$var wire 1 O PS2Clk_negedge $end
$var reg 2 P PS2Clk_sync [1:0] $end
$var reg 1 Q PS2Data $end
$var reg 1 R ack $end
$var reg 44 S buffer [43:0] $end
$var reg 6 T counter [5:0] $end
$var reg 44 U fifo [43:0] $end
$upscope $end
$scope task check_output $end
$var reg 1 V exp_left $end
$var reg 1 W exp_middle $end
$var reg 1 X exp_right $end
$var reg 8 Y exp_x [7:0] $end
$var reg 1 Z exp_x_sign $end
$var reg 8 [ exp_y [7:0] $end
$var reg 1 \ exp_y_sign $end
$var reg 1600 ] test_name [1600:1] $end
$upscope $end
$scope task ps2_clock_pulse $end
$upscope $end
$scope task send_mouse_packet $end
$var reg 8 ^ byte1 [7:0] $end
$var reg 1 _ l_btn $end
$var reg 1 ` m_btn $end
$var reg 1 a r_btn $end
$var reg 8 b x_mov [7:0] $end
$var reg 1 c x_sgn $end
$var reg 8 d y_mov [7:0] $end
$var reg 1 e y_sgn $end
$upscope $end
$scope task send_ps2_packet $end
$var reg 8 f data [7:0] $end
$var reg 1 g parity_bit $end
$var integer 32 h i [31:0] $end
$upscope $end
$upscope $end
$enddefinitions $end
$comment Show the parameter values. $end
$dumpall
$end
#0
$dumpvars
bx h
xg
bx f
xe
bx d
xc
bx b
xa
x`
x_
bx ^
bx ]
x\
bx [
xZ
bx Y
xX
xW
xV
b0 U
b0 T
b0 S
0R
0Q
b1 P
0O
0N
0M
0L
0K
b0 J
b0 I
b0 H
b0 G
0F
0E
0D
0C
0B
0A
0@
0?
b0 >
b0 =
b0 <
b0 ;
b0 :
b0 9
08
07
06
05
z4
03
12
01
00
0/
b0 .
b0 -
b0 ,
1+
1*
1)
0(
0'
0&
0%
b0 $
0#
b0 "
0!
$end
#5000
b11 P
1(
#10000
0(
#15000
1(
#20000
0(
#25000
1(
#30000
0(
#35000
1(
#40000
0(
#45000
1(
#50000
0(
#55000
1(
#60000
0(
#65000
1(
#70000
0(
#75000
1(
#80000
0(
#85000
1(
#90000
0(
#95000
1(
#100000
0(
#105000
1(
#110000
0(
#115000
1(
#120000
0(
#125000
1(
#130000
0(
#135000
1(
#140000
0(
#145000
1(
#150000
0(
#155000
1(
#160000
0(
#165000
1(
#170000
0(
#175000
1(
#180000
0(
#185000
1(
#190000
0(
#195000
1(
#200000
0(
0+
#205000
1Q
1(
#210000
0(
#215000
1(
#220000
0(
#225000
1(
#230000
0(
#235000
1(
#240000
0(
#245000
1(
#250000
0(
#255000
1(
#260000
0(
#265000
1(
#270000
0(
#275000
1(
#280000
0(
#285000
1(
#290000
0(
#295000
1(
#300000
0(
0*
0g
b1000 f
b1000 ^
b10100 d
b1010 b
0e
0c
0`
0a
0_
#305000
0Q
1(
#310000
0(
#315000
1(
#320000
0(
#325000
1(
#330000
0(
#335000
1(
#340000
0(
#345000
1(
#350000
0(
#355000
1(
#360000
0(
#365000
1(
#370000
0(
#375000
1(
#380000
0(
#385000
1(
#390000
0(
#395000
1(
#400000
0(
0)
#405000
1O
b10 P
1(
#410000
0(
#415000
b1 T
0O
b0 P
1(
#420000
0(
#425000
1(
#430000
0(
#435000
1(
#440000
0(
#445000
1(
#450000
0(
#455000
1(
#460000
0(
#465000
1(
#470000
0(
#475000
1(
#480000
0(
#485000
1(
#490000
0(
#495000
1(
#500000
0(
b0 h
1)
#505000
b1 P
1(
#510000
0(
#515000
b11 P
1(
#520000
0(
#525000
1(
#530000
0(
#535000
1(
#540000
0(
#545000
1(
#550000
0(
#555000
1(
#560000
0(
#565000
1(
#570000
0(
#575000
1(
#580000
0(
#585000
1(
#590000
0(
#595000
1(
#600000
0(
0)
#605000
1O
b10 P
1(
#610000
0(
#615000
b10 T
0O
b0 P
1(
#620000
0(
#625000
1(
#630000
0(
#635000
1(
#640000
0(
#645000
1(
#650000
0(
#655000
1(
#660000
0(
#665000
1(
#670000
0(
#675000
1(
#680000
0(
#685000
1(
#690000
0(
#695000
1(
#700000
0(
b1 h
1)
#705000
b1 P
1(
#710000
0(
#715000
b11 P
1(
#720000
0(
#725000
1(
#730000
0(
#735000
1(
#740000
0(
#745000
1(
#750000
0(
#755000
1(
#760000
0(
#765000
1(
#770000
0(
#775000
1(
#780000
0(
#785000
1(
#790000
0(
#795000
1(
#800000
0(
0)
#805000
1O
b10 P
1(
#810000
0(
#815000
b11 T
0O
b0 P
1(
#820000
0(
#825000
1(
#830000
0(
#835000
1(
#840000
0(
#845000
1(
#850000
0(
#855000
1(
#860000
0(
#865000
1(
#870000
0(
#875000
1(
#880000
0(
#885000
1(
#890000
0(
#895000
1(
#900000
0(
b10 h
1)
#905000
b1 P
1(
#910000
0(
#915000
b11 P
1(
#920000
0(
#925000
1(
#930000
0(
#935000
1(
#940000
0(
#945000
1(
#950000
0(
#955000
1(
#960000
0(
#965000
1(
#970000
0(
#975000
1(
#980000
0(
#985000
1(
#990000
0(
#995000
1(
#1000000
0(
0)
#1005000
1O
b10 P
1(
#1010000
0(
#1015000
b100 T
0O
b0 P
1(
#1020000
0(
#1025000
1(
#1030000
0(
#1035000
1(
#1040000
0(
#1045000
1(
#1050000
0(
#1055000
1(
#1060000
0(
#1065000
1(
#1070000
0(
#1075000
1(
#1080000
0(
#1085000
1(
#1090000
0(
#1095000
1(
#1100000
0(
1*
b11 h
1)
#1105000
1Q
b1 P
1(
#1110000
0(
#1115000
b11 P
1(
#1120000
0(
#1125000
1(
#1130000
0(
#1135000
1(
#1140000
0(
#1145000
1(
#1150000
0(
#1155000
1(
#1160000
0(
#1165000
1(
#1170000
0(
#1175000
1(
#1180000
0(
#1185000
1(
#1190000
0(
#1195000
1(
#1200000
0(
0)
#1205000
1O
b10 P
1(
#1210000
0(
#1215000
b101 T
b1 S
0O
b0 P
1(
#1220000
0(
#1225000
1(
#1230000
0(
#1235000
1(
#1240000
0(
#1245000
1(
#1250000
0(
#1255000
1(
#1260000
0(
#1265000
1(
#1270000
0(
#1275000
1(
#1280000
0(
#1285000
1(
#1290000
0(
#1295000
1(
#1300000
0(
0*
b100 h
1)
#1305000
0Q
b1 P
1(
#1310000
0(
#1315000
b11 P
1(
#1320000
0(
#1325000
1(
#1330000
0(
#1335000
1(
#1340000
0(
#1345000
1(
#1350000
0(
#1355000
1(
#1360000
0(
#1365000
1(
#1370000
0(
#1375000
1(
#1380000
0(
#1385000
1(
#1390000
0(
#1395000
1(
#1400000
0(
0)
#1405000
1O
b10 P
1(
#1410000
0(
#1415000
b110 T
b10 S
0O
b0 P
1(
#1420000
0(
#1425000
1(
#1430000
0(
#1435000
1(
#1440000
0(
#1445000
1(
#1450000
0(
#1455000
1(
#1460000
0(
#1465000
1(
#1470000
0(
#1475000
1(
#1480000
0(
#1485000
1(
#1490000
0(
#1495000
1(
#1500000
0(
b101 h
1)
#1505000
b1 P
1(
#1510000
0(
#1515000
b11 P
1(
#1520000
0(
#1525000
1(
#1530000
0(
#1535000
1(
#1540000
0(
#1545000
1(
#1550000
0(
#1555000
1(
#1560000
0(
#1565000
1(
#1570000
0(
#1575000
1(
#1580000
0(
#1585000
1(
#1590000
0(
#1595000
1(
#1600000
0(
0)
#1605000
1O
b10 P
1(
#1610000
0(
#1615000
b111 T
b100 S
0O
b0 P
1(
#1620000
0(
#1625000
1(
#1630000
0(
#1635000
1(
#1640000
0(
#1645000
1(
#1650000
0(
#1655000
1(
#1660000
0(
#1665000
1(
#1670000
0(
#1675000
1(
#1680000
0(
#1685000
1(
#1690000
0(
#1695000
1(
#1700000
0(
b110 h
1)
#1705000
b1 P
1(
#1710000
0(
#1715000
b11 P
1(
#1720000
0(
#1725000
1(
#1730000
0(
#1735000
1(
#1740000
0(
#1745000
1(
#1750000
0(
#1755000
1(
#1760000
0(
#1765000
1(
#1770000
0(
#1775000
1(
#1780000
0(
#1785000
1(
#1790000
0(
#1795000
1(
#1800000
0(
0)
#1805000
1O
b10 P
1(
#1810000
0(
#1815000
b1000 T
b1000 S
0O
b0 P
1(
#1820000
0(
#1825000
1(
#1830000
0(
#1835000
1(
#1840000
0(
#1845000
1(
#1850000
0(
#1855000
1(
#1860000
0(
#1865000
1(
#1870000
0(
#1875000
1(
#1880000
0(
#1885000
1(
#1890000
0(
#1895000
1(
#1900000
0(
b111 h
1)
#1905000
b1 P
1(
#1910000
0(
#1915000
b11 P
1(
#1920000
0(
#1925000
1(
#1930000
0(
#1935000
1(
#1940000
0(
#1945000
1(
#1950000
0(
#1955000
1(
#1960000
0(
#1965000
1(
#1970000
0(
#1975000
1(
#1980000
0(
#1985000
1(
#1990000
0(
#1995000
1(
#2000000
0(
0)
#2005000
1O
b10 P
1(
#2010000
0(
#2015000
b1001 T
b10000 S
0O
b0 P
1(
#2020000
0(
#2025000
1(
#2030000
0(
#2035000
1(
#2040000
0(
#2045000
1(
#2050000
0(
#2055000
1(
#2060000
0(
#2065000
1(
#2070000
0(
#2075000
1(
#2080000
0(
#2085000
1(
#2090000
0(
#2095000
1(
#2100000
0(
b1000 h
1)
#2105000
b1 P
1(
#2110000
0(
#2115000
b11 P
1(
#2120000
0(
#2125000
1(
#2130000
0(
#2135000
1(
#2140000
0(
#2145000
1(
#2150000
0(
#2155000
1(
#2160000
0(
#2165000
1(
#2170000
0(
#2175000
1(
#2180000
0(
#2185000
1(
#2190000
0(
#2195000
1(
#2200000
0(
0)
#2205000
1O
b10 P
1(
#2210000
0(
#2215000
b1010 T
b100000 S
0O
b0 P
1(
#2220000
0(
#2225000
1(
#2230000
0(
#2235000
1(
#2240000
0(
#2245000
1(
#2250000
0(
#2255000
1(
#2260000
0(
#2265000
1(
#2270000
0(
#2275000
1(
#2280000
0(
#2285000
1(
#2290000
0(
#2295000
1(
#2300000
0(
1*
1)
#2305000
1Q
b1 P
1(
#2310000
0(
#2315000
b11 P
1(
#2320000
0(
#2325000
1(
#2330000
0(
#2335000
1(
#2340000
0(
#2345000
1(
#2350000
0(
#2355000
1(
#2360000
0(
#2365000
1(
#2370000
0(
#2375000
1(
#2380000
0(
#2385000
1(
#2390000
0(
#2395000
1(
#2400000
0(
0)
#2405000
1O
b10 P
1(
#2410000
0(
#2415000
b1011 T
b1000001 S
0O
b0 P
1(
#2420000
0(
#2425000
1(
#2430000
0(
#2435000
1(
#2440000
0(
#2445000
1(
#2450000
0(
#2455000
1(
#2460000
0(
#2465000
1(
#2470000
0(
#2475000
1(
#2480000
0(
#2485000
1(
#2490000
0(
#2495000
1(
#2500000
0(
0*
1g
b1010 f
1)
#2505000
0Q
b1 P
1(
#2510000
0(
#2515000
b11 P
1(
#2520000
0(
#2525000
1(
#2530000
0(
#2535000
1(
#2540000
0(
#2545000
1(
#2550000
0(
#2555000
1(
#2560000
0(
#2565000
1(
#2570000
0(
#2575000
1(
#2580000
0(
#2585000
1(
#2590000
0(
#2595000
1(
#2600000
0(
0)
#2605000
1O
b10 P
1(
#2610000
0(
#2615000
b1100 T
b10000010 S
0O
b0 P
1(
#2620000
0(
#2625000
1(
#2630000
0(
#2635000
1(
#2640000
0(
#2645000
1(
#2650000
0(
#2655000
1(
#2660000
0(
#2665000
1(
#2670000
0(
#2675000
1(
#2680000
0(
#2685000
1(
#2690000
0(
#2695000
1(
#2700000
0(
b0 h
1)
#2705000
b1 P
1(
#2710000
0(
#2715000
b11 P
1(
#2720000
0(
#2725000
1(
#2730000
0(
#2735000
1(
#2740000
0(
#2745000
1(
#2750000
0(
#2755000
1(
#2760000
0(
#2765000
1(
#2770000
0(
#2775000
1(
#2780000
0(
#2785000
1(
#2790000
0(
#2795000
1(
#2800000
0(
0)
#2805000
1O
b10 P
1(
#2810000
0(
#2815000
b1101 T
b100000100 S
0O
b0 P
1(
#2820000
0(
#2825000
1(
#2830000
0(
#2835000
1(
#2840000
0(
#2845000
1(
#2850000
0(
#2855000
1(
#2860000
0(
#2865000
1(
#2870000
0(
#2875000
1(
#2880000
0(
#2885000
1(
#2890000
0(
#2895000
1(
#2900000
0(
1*
b1 h
1)
#2905000
1Q
b1 P
1(
#2910000
0(
#2915000
b11 P
1(
#2920000
0(
#2925000
1(
#2930000
0(
#2935000
1(
#2940000
0(
#2945000
1(
#2950000
0(
#2955000
1(
#2960000
0(
#2965000
1(
#2970000
0(
#2975000
1(
#2980000
0(
#2985000
1(
#2990000
0(
#2995000
1(
#3000000
0(
0)
#3005000
1O
b10 P
1(
#3010000
0(
#3015000
b1110 T
b1000001001 S
0O
b0 P
1(
#3020000
0(
#3025000
1(
#3030000
0(
#3035000
1(
#3040000
0(
#3045000
1(
#3050000
0(
#3055000
1(
#3060000
0(
#3065000
1(
#3070000
0(
#3075000
1(
#3080000
0(
#3085000
1(
#3090000
0(
#3095000
1(
#3100000
0(
0*
b10 h
1)
#3105000
0Q
b1 P
1(
#3110000
0(
#3115000
b11 P
1(
#3120000
0(
#3125000
1(
#3130000
0(
#3135000
1(
#3140000
0(
#3145000
1(
#3150000
0(
#3155000
1(
#3160000
0(
#3165000
1(
#3170000
0(
#3175000
1(
#3180000
0(
#3185000
1(
#3190000
0(
#3195000
1(
#3200000
0(
0)
#3205000
1O
b10 P
1(
#3210000
0(
#3215000
b1111 T
b10000010010 S
0O
b0 P
1(
#3220000
0(
#3225000
1(
#3230000
0(
#3235000
1(
#3240000
0(
#3245000
1(
#3250000
0(
#3255000
1(
#3260000
0(
#3265000
1(
#3270000
0(
#3275000
1(
#3280000
0(
#3285000
1(
#3290000
0(
#3295000
1(
#3300000
0(
1*
b11 h
1)
#3305000
1Q
b1 P
1(
#3310000
0(
#3315000
b11 P
1(
#3320000
0(
#3325000
1(
#3330000
0(
#3335000
1(
#3340000
0(
#3345000
1(
#3350000
0(
#3355000
1(
#3360000
0(
#3365000
1(
#3370000
0(
#3375000
1(
#3380000
0(
#3385000
1(
#3390000
0(
#3395000
1(
#3400000
0(
0)
#3405000
1O
b10 P
1(
#3410000
0(
#3415000
b10000 T
b100000100101 S
0O
b0 P
1(
#3420000
0(
#3425000
1(
#3430000
0(
#3435000
1(
#3440000
0(
#3445000
1(
#3450000
0(
#3455000
1(
#3460000
0(
#3465000
1(
#3470000
0(
#3475000
1(
#3480000
0(
#3485000
1(
#3490000
0(
#3495000
1(
#3500000
0(
0*
b100 h
1)
#3505000
0Q
b1 P
1(
#3510000
0(
#3515000
b11 P
1(
#3520000
0(
#3525000
1(
#3530000
0(
#3535000
1(
#3540000
0(
#3545000
1(
#3550000
0(
#3555000
1(
#3560000
0(
#3565000
1(
#3570000
0(
#3575000
1(
#3580000
0(
#3585000
1(
#3590000
0(
#3595000
1(
#3600000
0(
0)
#3605000
1O
b10 P
1(
#3610000
0(
#3615000
b10001 T
b1000001001010 S
0O
b0 P
1(
#3620000
0(
#3625000
1(
#3630000
0(
#3635000
1(
#3640000
0(
#3645000
1(
#3650000
0(
#3655000
1(
#3660000
0(
#3665000
1(
#3670000
0(
#3675000
1(
#3680000
0(
#3685000
1(
#3690000
0(
#3695000
1(
#3700000
0(
b101 h
1)
#3705000
b1 P
1(
#3710000
0(
#3715000
b11 P
1(
#3720000
0(
#3725000
1(
#3730000
0(
#3735000
1(
#3740000
0(
#3745000
1(
#3750000
0(
#3755000
1(
#3760000
0(
#3765000
1(
#3770000
0(
#3775000
1(
#3780000
0(
#3785000
1(
#3790000
0(
#3795000
1(
#3800000
0(
0)
#3805000
1O
b10 P
1(
#3810000
0(
#3815000
b10010 T
b10000010010100 S
0O
b0 P
1(
#3820000
0(
#3825000
1(
#3830000
0(
#3835000
1(
#3840000
0(
#3845000
1(
#3850000
0(
#3855000
1(
#3860000
0(
#3865000
1(
#3870000
0(
#3875000
1(
#3880000
0(
#3885000
1(
#3890000
0(
#3895000
1(
#3900000
0(
b110 h
1)
#3905000
b1 P
1(
#3910000
0(
#3915000
b11 P
1(
#3920000
0(
#3925000
1(
#3930000
0(
#3935000
1(
#3940000
0(
#3945000
1(
#3950000
0(
#3955000
1(
#3960000
0(
#3965000
1(
